zakilla/__init__.py
zakilla/embed_create/__init__.py
zakilla/embed_create/methods.py
zakilla/paginator/__init__.py
zakilla/paginator/paginator.py
zakilla/paginator/types.py
zakilla/utils/__init__.py
zakilla/utils/input.py
zakilla-1.0.2.dist-info/licenses/LICENSE.md
zakilla-1.0.2.dist-info/METADATA
zakilla-1.0.2.dist-info/WHEEL
zakilla-1.0.2.dist-info/top_level.txt
zakilla-1.0.2.dist-info/RECORD
