Metadata-Version: 2.4
Name: zakilla
Version: 1.0.2
Summary: A modern, easy to use, and fully customizable pagination system for discord.py
Home-page: https://github.com/ZaaakW/zakilla
Author: ZaaakW
License-File: LICENSE.md
Dynamic: author
Dynamic: home-page
Dynamic: license-file
